metaclass/__init__.py
metaclass-1.1.dist-info/metadata.json
metaclass-1.1.dist-info/DESCRIPTION.rst
metaclass-1.1.dist-info/METADATA
metaclass-1.1.dist-info/WHEEL
metaclass-1.1.dist-info/top_level.txt
metaclass-1.1.dist-info/RECORD
