Metadata-Version: 2.0
Name: metaclass
Version: 1.1
Summary: Useful baseclasses for metaclasses
Home-page: https://github.com/tecki/metaclasses
Author: Martin Teichmann
Author-email: lkb.teichmann@gmail.com
License: PSF
Platform: UNKNOWN
Classifier: Development Status :: 3 - Alpha
Classifier: Intended Audience :: Developers
Classifier: License :: OSI Approved :: Python Software Foundation License
Classifier: Programming Language :: Python :: 2.7
Classifier: Programming Language :: Python :: 3
Classifier: Programming Language :: Python :: Implementation :: CPython
Classifier: Topic :: Software Development :: Libraries :: Python Modules
